gitignore.py
shipa-ci.py
shipa.py
shipa_ci-0.0.9.data/scripts/shipa-ci
shipa_ci-0.0.9.data/scripts/shipa-ci.py
tests/__init__.py
tests/test_gitignore.py
shipa_ci-0.0.9.dist-info/LICENSE
shipa_ci-0.0.9.dist-info/METADATA
shipa_ci-0.0.9.dist-info/WHEEL
shipa_ci-0.0.9.dist-info/top_level.txt
shipa_ci-0.0.9.dist-info/RECORD
